{"cameraMode":{"drawMode":0,"name":"Shaded","section":"Shading Mode"},"sceneLighting":true,"audioPlay":false,"sceneViewState":{"m_AlwaysRefresh":false,"showFog":true,"showSkybox":true,"showFlares":true,"showImageEffects":true,"showParticleSystems":true,"showVisualEffectGraphs":true,"m_FxEnabled":true},"in2DMode":false,"pivot":{"x":-6.265233039855957,"y":2.2631735801696779,"z":-4.066061496734619},"rotation":{"x":0.00237038335762918,"y":0.9965067505836487,"z":-0.07819641381502152,"w":0.030207283794879915},"size":0.6062180399894714,"orthographic":false}